snakelib/__init__.py
snakelib/timer.py
snakelib-0.0.1.dist-info/LICENSE
snakelib-0.0.1.dist-info/METADATA
snakelib-0.0.1.dist-info/WHEEL
snakelib-0.0.1.dist-info/top_level.txt
snakelib-0.0.1.dist-info/RECORD
