Metadata-Version: 2.1
Name: snakelib
Version: 0.0.1
Summary: Development tools
Home-page: https://github.com/snake-soft/snake-lib
Author: snake-soft
Author-email: info@snake-soft.com
License: UNKNOWN
Platform: UNKNOWN
Classifier: Programming Language :: Python :: 3
Classifier: License :: OSI Approved :: GNU General Public License v3 (GPLv3)
Classifier: Operating System :: OS Independent
Requires-Python: >=3.6
